setup.py
requests_vzauth/__init__.py
requests_vzauth/requests_vzauth.py
requests_vzauth.egg-info/PKG-INFO
requests_vzauth.egg-info/SOURCES.txt
requests_vzauth.egg-info/dependency_links.txt
requests_vzauth.egg-info/requires.txt
requests_vzauth.egg-info/top_level.txt