Metadata-Version: 1.1
Name: requests-vzauth
Version: 0.1.0
Summary: Verizon Cloud authentication handler for requests.
Home-page: https://github.com/replicant0wnz/requests-vzauth
Author: Glenn E. Bailey III
Author-email: replicant@dallaslamers.org
License: LICENSE
Platform: UNKNOWN
Classifier: License :: OSI Approved :: GNU General Public License v3 (GPLv3)
Classifier: Development Status :: 4 - Beta
Classifier: Intended Audience :: Developers
Classifier: Programming Language :: Python
Classifier: Programming Language :: Python :: 2.6
Classifier: Programming Language :: Python :: 2.7
Provides: requests_vzauth
